runtime_keypath/__init__.py
runtime_keypath/__test__.py
runtime_keypath/__typecheck__.py
runtime_keypath/_core.py
runtime_keypath/_sugarful.py
runtime_keypath/_sugarless.py
runtime_keypath/py.typed
runtime_keypath-0.2.0.dist-info/licenses/LICENSE
runtime_keypath-0.2.0.dist-info/METADATA
runtime_keypath-0.2.0.dist-info/WHEEL
runtime_keypath-0.2.0.dist-info/top_level.txt
runtime_keypath-0.2.0.dist-info/RECORD
