Metadata-Version: 2.4
Name: runtime-keypath
Version: 0.2.0
Summary: Supports runtime key-path recording/accessing for Python.
Author-email: Chris Fu <17433201@qq.com>
License: MIT License
Project-URL: Homepage, https://github.com/Azureblade3808/py-runtime-keypath
Project-URL: Bug Tracker, https://github.com/Azureblade3808/py-runtime-keypath/issues
Classifier: Programming Language :: Python :: 3
Classifier: License :: OSI Approved :: MIT License
Classifier: Operating System :: OS Independent
Classifier: Intended Audience :: Developers
Classifier: Development Status :: 3 - Alpha
Requires-Python: >=3.8
License-File: LICENSE
Dynamic: license-file
